RISC-V.srcs/sources_1/new/matrix_mul_accel.v
module matrix_mult_accel (
    input  wire        clk,
    input  wire        rst_n,
    input  wire [31:0] addr,
    input  wire [31:0] wdata,
    input  wire        we,
    output reg  [31:0] rdata
);

    // Accelerator registers (memory-mapped)
    reg [31:0] matrix_a [0:15];  // 4x4 matrix A
    reg [31:0] matrix_b [0:15];  // 4x4 matrix B
    reg [31:0] matrix_c [0:15];  // 4x4 result matrix C
    reg [31:0] control;          // Control register
    reg [31:0] status;           // Status register
    
    integer i, j, k;
    reg computing;
    reg [3:0] compute_state;
    
    // Memory map:
    // 0x10000000-0x1000003C: Matrix A (16 words)
    // 0x10000040-0x1000007C: Matrix B (16 words)
    // 0x10000080-0x100000BC: Matrix C (16 words - read only)
    // 0x100000C0: Control (write 1 to start)
    // 0x100000C4: Status (bit 0: busy, bit 1: done)
    
    wire [7:0] word_addr = addr[7:2];
    
    // Write operations
    always @(posedge clk or negedge rst_n) begin
        if (!rst_n) begin
            for (i = 0; i < 16; i = i + 1) begin
                matrix_a[i] <= 32'h0;
                matrix_b[i] <= 32'h0;
                matrix_c[i] <= 32'h0;
            end
            control <= 32'h0;
            status <= 32'h0;
            computing <= 1'b0;
            compute_state <= 4'h0;
        end else begin
            if (we) begin
                if (word_addr < 16) matrix_a[word_addr] <= wdata;
                else if (word_addr < 32) matrix_b[word_addr - 16] <= wdata;
                else if (word_addr == 48) begin
                    control <= wdata;
                    if (wdata[0]) begin
                        computing <= 1'b1;
                        status <= 32'h1; // Set busy
                        compute_state <= 4'h0;
                    end
                end
            end
            
            // Matrix multiplication state machine
            if (computing) begin
                if (compute_state < 4) begin
                    // Compute row compute_state of result
                    for (j = 0; j < 4; j = j + 1) begin
                        matrix_c[compute_state*4 + j] <= 
                            matrix_a[compute_state*4 + 0] * matrix_b[0*4 + j] +
                            matrix_a[compute_state*4 + 1] * matrix_b[1*4 + j] +
                            matrix_a[compute_state*4 + 2] * matrix_b[2*4 + j] +
                            matrix_a[compute_state*4 + 3] * matrix_b[3*4 + j];
                    end
                    compute_state <= compute_state + 1;
                end else begin
                    computing <= 1'b0;
                    status <= 32'h2; // Set done, clear busy
                    control <= 32'h0;
                end
            end
        end
    end
    
    // Read operations
    always @(*) begin
        if (word_addr < 16) rdata = matrix_a[word_addr];
        else if (word_addr < 32) rdata = matrix_b[word_addr - 16];
        else if (word_addr < 48) rdata = matrix_c[word_addr - 32];
        else if (word_addr == 48) rdata = control;
        else if (word_addr == 49) rdata = status;
        else rdata = 32'h0;
    end

endmodule

RISC-V.srcs/sources_1/new/memory.v
module memory #(
    parameter ADDR_WIDTH = 14,  // 16KB = 4K words
    parameter DATA_WIDTH = 32,
    parameter MEM_FILE = ""
)(
    input  wire                    clk,
    input  wire [ADDR_WIDTH-1:0]   addr,
    input  wire [DATA_WIDTH-1:0]   wdata,
    input  wire                    we,
    input  wire                    re,
    output reg  [DATA_WIDTH-1:0]   rdata
);

    reg [DATA_WIDTH-1:0] mem_array [0:(2**ADDR_WIDTH)-1];
    
    initial begin
        if (MEM_FILE != "") begin
            $readmemh(MEM_FILE, mem_array);
        end
    end
    
    always @(posedge clk) begin
        if (we) mem_array[addr] <= wdata;
        if (re) rdata <= mem_array[addr];
    end

endmodule

RISC-V.srcs/sources_1/new/riscv_core.v
module riscv_core (
    input  wire        clk,
    input  wire        rst_n,
    output wire [31:0] imem_addr,
    input  wire [31:0] imem_rdata,
    output wire [31:0] dmem_addr,
    output wire [31:0] dmem_wdata,
    output wire        dmem_we,
    output wire        dmem_re,
    input  wire [31:0] dmem_rdata,
    output wire [31:0] accel_addr,
    output wire [31:0] accel_wdata,
    output wire        accel_we,
    input  wire [31:0] accel_rdata
);

    // Program Counter
    reg [31:0] pc;
    wire [31:0] pc_next;
    wire [31:0] pc_plus4 = pc + 4;
    wire pc_sel;
    wire [31:0] pc_branch;
    
    always @(posedge clk or negedge rst_n) begin
        if (!rst_n) pc <= 32'h0;
        else pc <= pc_next;
    end
    
    assign imem_addr = pc;
    assign pc_next = pc_sel ? pc_branch : pc_plus4;
    
    // IF/ID Pipeline Register
    reg [31:0] if_id_instr, if_id_pc;
    
    always @(posedge clk or negedge rst_n) begin
        if (!rst_n) begin
            if_id_instr <= 32'h0;
            if_id_pc <= 32'h0;
        end else begin
            if_id_instr <= imem_rdata;
            if_id_pc <= pc;
        end
    end
    
    // Decode
    wire [6:0] opcode = if_id_instr[6:0];
    wire [4:0] rd = if_id_instr[11:7];
    wire [2:0] funct3 = if_id_instr[14:12];
    wire [4:0] rs1 = if_id_instr[19:15];
    wire [4:0] rs2 = if_id_instr[24:20];
    wire [6:0] funct7 = if_id_instr[31:25];
    
    // Register File (32 registers)
    reg [31:0] registers [0:31];
    integer i;
    
    wire [31:0] rs1_data = (rs1 == 0) ? 32'h0 : registers[rs1];
    wire [31:0] rs2_data = (rs2 == 0) ? 32'h0 : registers[rs2];
    
    // Immediate Generation
    wire [31:0] imm_i = {{20{if_id_instr[31]}}, if_id_instr[31:20]};
    wire [31:0] imm_s = {{20{if_id_instr[31]}}, if_id_instr[31:25], if_id_instr[11:7]};
    wire [31:0] imm_b = {{19{if_id_instr[31]}}, if_id_instr[31], if_id_instr[7], if_id_instr[30:25], if_id_instr[11:8], 1'b0};
    wire [31:0] imm_u = {if_id_instr[31:12], 12'h0};
    wire [31:0] imm_j = {{11{if_id_instr[31]}}, if_id_instr[31], if_id_instr[19:12], if_id_instr[20], if_id_instr[30:21], 1'b0};
    
    // ID/EX Pipeline Register
    reg [31:0] id_ex_rs1_data, id_ex_rs2_data, id_ex_imm, id_ex_pc;
    reg [4:0] id_ex_rd;
    reg [6:0] id_ex_opcode;
    reg [2:0] id_ex_funct3;
    reg [6:0] id_ex_funct7;
    
    always @(posedge clk or negedge rst_n) begin
        if (!rst_n) begin
            id_ex_rs1_data <= 32'h0;
            id_ex_rs2_data <= 32'h0;
            id_ex_imm <= 32'h0;
            id_ex_pc <= 32'h0;
            id_ex_rd <= 5'h0;
            id_ex_opcode <= 7'h0;
            id_ex_funct3 <= 3'h0;
            id_ex_funct7 <= 7'h0;
        end else begin
            id_ex_rs1_data <= rs1_data;
            id_ex_rs2_data <= rs2_data;
            id_ex_rd <= rd;
            id_ex_opcode <= opcode;
            id_ex_funct3 <= funct3;
            id_ex_funct7 <= funct7;
            id_ex_pc <= if_id_pc;
            
            case (opcode)
                7'b0010011, 7'b0000011, 7'b1100111: id_ex_imm <= imm_i;
                7'b0100011: id_ex_imm <= imm_s;
                7'b1100011: id_ex_imm <= imm_b;
                7'b0110111, 7'b0010111: id_ex_imm <= imm_u;
                7'b1101111: id_ex_imm <= imm_j;
                default: id_ex_imm <= 32'h0;
            endcase
        end
    end
    
    // Execute: ALU
    reg [31:0] alu_result;
    reg alu_zero;
    wire [31:0] alu_a = id_ex_rs1_data;
    wire [31:0] alu_b = (id_ex_opcode == 7'b0110011) ? id_ex_rs2_data : id_ex_imm;
    
    always @(*) begin
        case (id_ex_opcode)
            7'b0110011, 7'b0010011: begin // R-type and I-type
                case (id_ex_funct3)
                    3'b000: alu_result = (id_ex_opcode == 7'b0110011 && id_ex_funct7[5]) ? 
                                         alu_a - alu_b : alu_a + alu_b;
                    3'b001: alu_result = alu_a << alu_b[4:0];
                    3'b010: alu_result = ($signed(alu_a) < $signed(alu_b)) ? 32'h1 : 32'h0;
                    3'b011: alu_result = (alu_a < alu_b) ? 32'h1 : 32'h0;
                    3'b100: alu_result = alu_a ^ alu_b;
                    3'b101: alu_result = id_ex_funct7[5] ? 
                                         $signed(alu_a) >>> alu_b[4:0] : alu_a >> alu_b[4:0];
                    3'b110: alu_result = alu_a | alu_b;
                    3'b111: alu_result = alu_a & alu_b;
                    default: alu_result = 32'h0;
                endcase
            end
            7'b0000011, 7'b0100011: alu_result = alu_a + alu_b; // Load/Store
            7'b1100011: begin // Branch
                case (id_ex_funct3)
                    3'b000: alu_zero = (alu_a == alu_b);  // BEQ
                    3'b001: alu_zero = (alu_a != alu_b);  // BNE
                    3'b100: alu_zero = ($signed(alu_a) < $signed(alu_b));  // BLT
                    3'b101: alu_zero = ($signed(alu_a) >= $signed(alu_b)); // BGE
                    3'b110: alu_zero = (alu_a < alu_b);   // BLTU
                    3'b111: alu_zero = (alu_a >= alu_b);  // BGEU
                    default: alu_zero = 1'b0;
                endcase
                alu_result = alu_a + alu_b;
            end
            7'b0110111: alu_result = id_ex_imm; // LUI
            7'b0010111: alu_result = id_ex_pc + id_ex_imm; // AUIPC
            7'b1101111, 7'b1100111: alu_result = id_ex_pc + 4; // JAL/JALR
            default: alu_result = 32'h0;
        endcase
    end
    
    assign pc_branch = id_ex_pc + id_ex_imm;
    assign pc_sel = (id_ex_opcode == 7'b1100011 && alu_zero) || 
                    (id_ex_opcode == 7'b1101111) ||
                    (id_ex_opcode == 7'b1100111);
    
    // EX/MEM Pipeline Register
    reg [31:0] ex_mem_alu_result, ex_mem_rs2_data;
    reg [4:0] ex_mem_rd;
    reg [6:0] ex_mem_opcode;
    reg [2:0] ex_mem_funct3;
    
    always @(posedge clk or negedge rst_n) begin
        if (!rst_n) begin
            ex_mem_alu_result <= 32'h0;
            ex_mem_rs2_data <= 32'h0;
            ex_mem_rd <= 5'h0;
            ex_mem_opcode <= 7'h0;
            ex_mem_funct3 <= 3'h0;
        end else begin
            ex_mem_alu_result <= alu_result;
            ex_mem_rs2_data <= id_ex_rs2_data;
            ex_mem_rd <= id_ex_rd;
            ex_mem_opcode <= id_ex_opcode;
            ex_mem_funct3 <= id_ex_funct3;
        end
    end
    
    // Memory Access
    wire is_accel_addr = (ex_mem_alu_result >= 32'h10000000);
    
    assign dmem_addr = ex_mem_alu_result;
    assign dmem_wdata = ex_mem_rs2_data;
    assign dmem_we = (ex_mem_opcode == 7'b0100011) && !is_accel_addr;
    assign dmem_re = (ex_mem_opcode == 7'b0000011) && !is_accel_addr;
    
    assign accel_addr = ex_mem_alu_result;
    assign accel_wdata = ex_mem_rs2_data;
    assign accel_we = (ex_mem_opcode == 7'b0100011) && is_accel_addr;
    
    wire [31:0] mem_rdata = is_accel_addr ? accel_rdata : dmem_rdata;
    
    // MEM/WB Pipeline Register
    reg [31:0] mem_wb_alu_result, mem_wb_mem_data;
    reg [4:0] mem_wb_rd;
    reg [6:0] mem_wb_opcode;
    
    always @(posedge clk or negedge rst_n) begin
        if (!rst_n) begin
            mem_wb_alu_result <= 32'h0;
            mem_wb_mem_data <= 32'h0;
            mem_wb_rd <= 5'h0;
            mem_wb_opcode <= 7'h0;
        end else begin
            mem_wb_alu_result <= ex_mem_alu_result;
            mem_wb_mem_data <= mem_rdata;
            mem_wb_rd <= ex_mem_rd;
            mem_wb_opcode <= ex_mem_opcode;
        end
    end
    
    // Write Back
    wire [31:0] wb_data = (mem_wb_opcode == 7'b0000011) ? mem_wb_mem_data : mem_wb_alu_result;
    wire wb_enable = (mem_wb_rd != 0) && 
                     (mem_wb_opcode == 7'b0110011 || mem_wb_opcode == 7'b0010011 ||
                      mem_wb_opcode == 7'b0000011 || mem_wb_opcode == 7'b0110111 ||
                      mem_wb_opcode == 7'b0010111 || mem_wb_opcode == 7'b1101111 ||
                      mem_wb_opcode == 7'b1100111);
    
    always @(posedge clk or negedge rst_n) begin
        if (!rst_n) begin
            for (i = 0; i < 32; i = i + 1) registers[i] <= 32'h0;
        end else if (wb_enable) begin
            registers[mem_wb_rd] <= wb_data;
        end
    end

endmodule

RISC-V.srcs/sources_1/new/riscv_soc.v
module riscv_soc (
    input  wire clk,
    input  wire rst_n,
    output wire [7:0] debug_pc
);

    wire [31:0] imem_addr, imem_rdata;
    wire [31:0] dmem_addr, dmem_wdata, dmem_rdata;
    wire dmem_we, dmem_re;
    wire [31:0] accel_addr, accel_wdata, accel_rdata;
    wire accel_we;
    
    assign debug_pc = imem_addr[9:2];
    
    riscv_core cpu (
        .clk(clk),
        .rst_n(rst_n),
        .imem_addr(imem_addr),
        .imem_rdata(imem_rdata),
        .dmem_addr(dmem_addr),
        .dmem_wdata(dmem_wdata),
        .dmem_we(dmem_we),
        .dmem_re(dmem_re),
        .dmem_rdata(dmem_rdata),
        .accel_addr(accel_addr),
        .accel_wdata(accel_wdata),
        .accel_we(accel_we),
        .accel_rdata(accel_rdata)
    );
    
    memory #(
        .ADDR_WIDTH(12),
        .MEM_FILE("program.hex")
    ) imem (
        .clk(clk),
        .addr(imem_addr[13:2]),
        .wdata(32'h0),
        .we(1'b0),
        .re(1'b1),
        .rdata(imem_rdata)
    );
    
    memory #(
        .ADDR_WIDTH(12),
        .MEM_FILE("")
    ) dmem (
        .clk(clk),
        .addr(dmem_addr[13:2]),
        .wdata(dmem_wdata),
        .we(dmem_we),
        .re(dmem_re),
        .rdata(dmem_rdata)
    );
    
    matrix_mult_accel accelerator (
        .clk(clk),
        .rst_n(rst_n),
        .addr(accel_addr),
        .wdata(accel_wdata),
        .we(accel_we),
        .rdata(accel_rdata)
    );

endmodule

RISC-V.srcs/sim_1/new/tb_riscv_soc.v
`timescale 1ns/1ps

module tb_riscv_soc;

    reg clk, rst_n;
    wire [7:0] debug_pc;
    
    riscv_soc dut (
        .clk(clk),
        .rst_n(rst_n),
        .debug_pc(debug_pc)
    );
    
    initial begin
        clk = 0;
        forever #5 clk = ~clk; // 100MHz clock
    end
    
    initial begin
        rst_n = 0;
        #20 rst_n = 1;
        
        #10000;
        
        $display("Simulation Complete");
        $finish;
    end
    
    initial begin
        $dumpfile("riscv_soc.vcd");
        $dumpvars(0, tb_riscv_soc);
    end

endmodule

RISC-V.sim/sim_1/behav/xsim/riscv_soc.vcd
$date
   Sun Jan  4 17:47:50 2026
$end

$version
  2025.2
  $dumpfile ("riscv_soc.vcd") 
$end

$timescale
  1ps
$end

$scope module tb_riscv_soc $end
$var reg 1 ! clk $end
$var reg 1 " rst_n $end
$var wire 8 # debug_pc [7:0] $end
$scope module dut $end
$var wire 1 $ clk $end
$var wire 1 % rst_n $end
$var wire 8 # debug_pc [7:0] $end
$var wire 32 & imem_addr [31:0] $end
$var wire 32 ' imem_rdata [31:0] $end
$var wire 32 ( dmem_addr [31:0] $end
$var wire 32 ) dmem_wdata [31:0] $end
$var wire 32 * dmem_rdata [31:0] $end
$var wire 1 + dmem_we $end
$var wire 1 , dmem_re $end
$var wire 32 - accel_addr [31:0] $end
$var wire 32 . accel_wdata [31:0] $end
$var wire 32 / accel_rdata [31:0] $end
$var wire 1 0 accel_we $end
$scope module cpu $end
$var wire 1 $ clk $end
$var wire 1 % rst_n $end
$var wire 32 & imem_addr [31:0] $end
$var wire 32 ' imem_rdata [31:0] $end
$var wire 32 ( dmem_addr [31:0] $end
$var wire 32 ) dmem_wdata [31:0] $end
$var wire 1 + dmem_we $end
$var wire 1 , dmem_re $end
$var wire 32 * dmem_rdata [31:0] $end
$var wire 32 - accel_addr [31:0] $end
$var wire 32 . accel_wdata [31:0] $end
$var wire 1 0 accel_we $end
$var wire 32 / accel_rdata [31:0] $end
$var reg 32 1 pc [31:0] $end
$var wire 32 2 pc_next [31:0] $end
$var wire 32 3 pc_plus4 [31:0] $end
$var wire 1 4 pc_sel $end
$var wire 32 5 pc_branch [31:0] $end
$var reg 32 6 if_id_instr [31:0] $end
$var reg 32 7 if_id_pc [31:0] $end
$var wire 7 8 opcode [6:0] $end
$var wire 5 9 rd [4:0] $end
$var wire 3 : funct3 [2:0] $end
$var wire 5 ; rs1 [4:0] $end
$var wire 5 < rs2 [4:0] $end
$var wire 7 = funct7 [6:0] $end
$var integer 32 > i [31:0] $end
$var wire 32 ? rs1_data [31:0] $end
$var wire 32 @ rs2_data [31:0] $end
$var wire 32 A imm_i [31:0] $end
$var wire 32 B imm_s [31:0] $end
$var wire 32 C imm_b [31:0] $end
$var wire 32 D imm_u [31:0] $end
$var wire 32 E imm_j [31:0] $end
$var reg 32 F id_ex_rs1_data [31:0] $end
$var reg 32 G id_ex_rs2_data [31:0] $end
$var reg 32 H id_ex_imm [31:0] $end
$var reg 32 I id_ex_pc [31:0] $end
$var reg 5 J id_ex_rd [4:0] $end
$var reg 7 K id_ex_opcode [6:0] $end
$var reg 3 L id_ex_funct3 [2:0] $end
$var reg 7 M id_ex_funct7 [6:0] $end
$var reg 32 N alu_result [31:0] $end
$var reg 1 O alu_zero $end
$var wire 32 P alu_a [31:0] $end
$var wire 32 Q alu_b [31:0] $end
$var reg 32 R ex_mem_alu_result [31:0] $end
$var reg 32 S ex_mem_rs2_data [31:0] $end
$var reg 5 T ex_mem_rd [4:0] $end
$var reg 7 U ex_mem_opcode [6:0] $end
$var reg 3 V ex_mem_funct3 [2:0] $end
$var wire 1 W is_accel_addr $end
$var wire 32 X mem_rdata [31:0] $end
$var reg 32 Y mem_wb_alu_result [31:0] $end
$var reg 32 Z mem_wb_mem_data [31:0] $end
$var reg 5 [ mem_wb_rd [4:0] $end
$var reg 7 \ mem_wb_opcode [6:0] $end
$var wire 32 ] wb_data [31:0] $end
$var wire 1 ^ wb_enable $end
$upscope $end
$scope module imem $end
$var wire 1 $ clk $end
$var wire 12 _ addr [13:2] $end
$var wire 32 ` wdata [31:0] $end
$var wire 1 a we $end
$var wire 1 b re $end
$var reg 32 c rdata [31:0] $end
$upscope $end
$scope module dmem $end
$var wire 1 $ clk $end
$var wire 12 d addr [13:2] $end
$var wire 32 ) wdata [31:0] $end
$var wire 1 + we $end
$var wire 1 , re $end
$var reg 32 e rdata [31:0] $end
$upscope $end
$scope module accelerator $end
$var wire 1 $ clk $end
$var wire 1 % rst_n $end
$var wire 32 - addr [31:0] $end
$var wire 32 . wdata [31:0] $end
$var wire 1 0 we $end
$var reg 32 f rdata [31:0] $end
$var reg 32 g control [31:0] $end
$var reg 32 h status [31:0] $end
$var integer 32 i i [31:0] $end
$var integer 32 j j [31:0] $end
$var integer 32 k k [31:0] $end
$var reg 1 l computing $end
$var reg 4 m compute_state [3:0] $end
$var wire 8 n word_addr [7:0] $end
$upscope $end
$upscope $end
$upscope $end
$enddefinitions $end

#0
$dumpvars
0!
0"
b0 #
0$
0%
b0 &
bx '
b0 (
b0 )
bx *
0+
0,
b0 -
b0 .
b0 /
00
b0 1
b100 2
b100 3
04
b0 5
b0 6
b0 7
b0 8
b0 9
b0 :
b0 ;
b0 <
b0 =
bx >
b0 ?
b0 @
b0 A
b0 B
b0 C
b0 D
b0 E
b0 F
b0 G
b0 H
b0 I
b0 J
b0 K
b0 L
b0 M
b0 N
xO
b0 P
b0 Q
b0 R
b0 S
b0 T
b0 U
b0 V
0W
bx X
b0 Y
b0 Z
b0 [
b0 \
b0 ]
0^
b0 _
b0 `
0a
1b
bx c
b0 d
bx e
b0 f
b0 g
b0 h
bx i
bx j
bx k
0l
b0 m
b0 n
$end

#5000
1!
1$

#10000
0!
0$

#15000
1!
1$

#20000
0!
1"
0$
1%

#25000
1!
b1 #
1$
b100 &
b100 1
b1000 2
b1000 3
bx 6
bx 8
bx 9
bx :
bx ;
bx <
bx =
bx ?
bx @
bx A
bx B
bx0 C
bx000000000000 D
bx0 E
bx Z
b1 _

#30000
0!
0$

#35000
1!
b10 #
1$
b1000 &
b1000 1
b0xx00 2
b1100 3
x4
b100 7
bx F
bx G
bx J
bx K
bx L
bx M
bx P
bx Q
b10 _

#40000
0!
0$

#45000
1!
b0xx #
1$
b0xx00 &
bx )
x+
x,
bx .
b0xx00 1
bx 2
bx 3
b100 5
b1000 7
b100 I
bx S
bx T
bx U
bx V
b0xx _

#50000
0!
0$

#55000
1!
bx #
1$
bx &
bx 1
b1000 5
b0xx00 7
b1000 I
bx [
bx \
bx ]
x^
bx _

#60000
0!
0$

#65000
1!
1$
bx 5
bx 7
b0xx00 I

#70000
0!
0$

#75000
1!
1$
bx I

